src/CalculateMean.py
src/__init__.py
CalculateMean_Class-0.1.1.dist-info/LICENCE
CalculateMean_Class-0.1.1.dist-info/METADATA
CalculateMean_Class-0.1.1.dist-info/WHEEL
CalculateMean_Class-0.1.1.dist-info/top_level.txt
CalculateMean_Class-0.1.1.dist-info/RECORD
